range_numbers_sum_lib/__init__.py
range_numbers_sum_lib/__main__.py
range_numbers_sum_lib/core.py
rangenumberssumlibrary-0.1.0.dist-info/licenses/LICENSE
rangenumberssumlibrary-0.1.0.dist-info/METADATA
rangenumberssumlibrary-0.1.0.dist-info/WHEEL
rangenumberssumlibrary-0.1.0.dist-info/entry_points.txt
rangenumberssumlibrary-0.1.0.dist-info/top_level.txt
rangenumberssumlibrary-0.1.0.dist-info/RECORD
