Metadata-Version: 2.4
Name: RangeNumbersSumLibrary
Version: 0.1.0
Summary: Calculate sum of numbers in a range from a to b
Author: Suhail Nabil Alansi
Author-email: Suhail Nabil Alansi <suhail09t12@gmail.com>
License: MIT License
Requires-Python: >=3.7
License-File: LICENSE
Dynamic: author
Dynamic: license-file
Dynamic: requires-python
